MT_PY_File_upload/__init__.py
MT_PY_File_upload/azureBlobStorage.py
MT_PY_File_upload/file_upload.py
MT_PY_File_upload/upload_file_to_s3.py
MT_PY_File_upload/validators.py
MT_PY_File_upload-0.2.4.dist-info/LICENSE
MT_PY_File_upload-0.2.4.dist-info/METADATA
MT_PY_File_upload-0.2.4.dist-info/WHEEL
MT_PY_File_upload-0.2.4.dist-info/top_level.txt
MT_PY_File_upload-0.2.4.dist-info/RECORD
