Metadata-Version: 2.1
Name: MT-PY-File-upload
Version: 0.2.4
Summary: A package to implementing file upload in AWS s3 bucket and store mysqlite,msql,postgress,Azure Blob
Author-email: Viraj <virajpoojari0905@gmail.com>
Project-URL: Homepage, https://github.com/pypa/sampleproject
Project-URL: Bug Tracker, https://github.com/pypa/sampleproject/issues
Classifier: Programming Language :: Python :: 3
Classifier: License :: OSI Approved :: MIT License
Classifier: Operating System :: OS Independent
Requires-Python: >=3.7
License-File: LICENSE
